src/BestOptimalAlgo.py
src/__init__.py
src/utils.py
src/best_optimal_algo/__init__.py
src/components/__init__.py
src/components/suppliments.py
best_optimal_algo-0.0.2.dist-info/LICENSE
best_optimal_algo-0.0.2.dist-info/METADATA
best_optimal_algo-0.0.2.dist-info/WHEEL
best_optimal_algo-0.0.2.dist-info/top_level.txt
best_optimal_algo-0.0.2.dist-info/RECORD
